tioe1.v
// Tiongquico, Erik Lance L. (S11)
/*
    Boolean Function
    F =(AB' + A'B) (C+D')

*/
module tioe1(F, A, B, C, D);
    output F;
    input A, B, C, D;

    assign F = ( (A && !B) || (!A && B) ) && (C && !D);


endmodule

tioe1_tb.v
// Tiongquico, Erik Lance L. (S11)
module tioe1_tb();
    reg [3:0] t_input;
    wire t_F;

    tioe1 dut(t_F, t_input[3], t_input[2], t_input[1], t_input[0]);

    initial begin
        t_input = 4'b0000;
        repeat(16)
            #10 t_input = t_input + 4'b0001;
    end

    initial begin
        $display("Written by Erik Lance Tiongquico - S11");
        $display("(AB' + A'B) (C+D')");
        $display("Verilog Dataflow Model");
        $monitor("time = %0d ", $time, "A = %b B = %b C = %b D = %b output_F = %b", t_input[3], t_input[2], t_input[1], t_input[0], t_F);
        $dumpfile("tioe1.vcd");
        $dumpvars();
    end

endmodule

tioe1.vcd
$date
	Thu Apr 28 18:37:41 2022
$end
$version
	Icarus Verilog
$end
$timescale
	1s
$end
$scope module tioe1_tb $end
$var wire 1 ! t_F $end
$var reg 4 " t_input [3:0] $end
$scope module dut $end
$var wire 1 # A $end
$var wire 1 $ B $end
$var wire 1 % C $end
$var wire 1 & D $end
$var wire 1 ! F $end
$upscope $end
$upscope $end
$enddefinitions $end
#0
$dumpvars
0&
0%
0$
0#
b0 "
0!
$end
#10
1&
b1 "
#20
1%
0&
b10 "
#30
1&
b11 "
#40
1!
1$
0%
0&
b100 "
#50
0!
1&
b101 "
#60
1!
1%
0&
b110 "
#70
1&
b111 "
#80
1#
0$
0%
0&
b1000 "
#90
0!
1&
b1001 "
#100
1!
1%
0&
b1010 "
#110
1&
b1011 "
#120
0!
1$
0%
0&
b1100 "
#130
1&
b1101 "
#140
1%
0&
b1110 "
#150
1&
b1111 "
#160
0#
0$
0%
0&
b0 "
